slack_exception_messages/__init__.py
slack_exception_messages/log.py
except_slack-0.1.dist-info/LICENSE
except_slack-0.1.dist-info/METADATA
except_slack-0.1.dist-info/WHEEL
except_slack-0.1.dist-info/top_level.txt
except_slack-0.1.dist-info/RECORD
